{
  "data": [
    {
      "Frame": 301,
      "FocusedName": "Fropp",
      "LocalPosition": {
        "x": 2.3086579443598665,
        "y": 0.6549318516316708,
        "z": -0.9777781504061811
      },
      "LocalRotation": {
        "x": -14.011731195345789,
        "y": -78.59297717733948,
        "z": 0
      },
      "ModelWorldPosition": {
        "x": 0,
        "y": 0,
        "z": 0
      },
      "ModelWorldRotation": {
        "x": 0.0,
        "y": 41.36733,
        "z": 0.0
      }
    },
    {
      "Frame": 302,
      "FocusedName": "Fropp",
      "LocalPosition": {
        "x": 2.3450387505476824,
        "y": 0.6589199188863386,
        "z": -1.0038200587083423
      },
      "LocalRotation": {
        "x": -13.294353249435744,
        "y": -76.92398435894415,
        "z": 0
      },
      "ModelWorldPosition": {
        "x": 0,
        "y": 0,
        "z": 0
      },
      "ModelWorldRotation": {
        "x": 0.0,
        "y": 41.36733,
        "z": 0.0
      }
    },
    {
      "Frame": 303,
      "FocusedName": "Fropp",
      "LocalPosition": {
        "x": 2.310591589365457,
        "y": 0.6598939308565682,
        "z": -0.9761455036990215
      },
      "LocalRotation": {
        "x": -13.473128021835166,
        "y": -76.54617860170438,
        "z": 0
      },
      "ModelWorldPosition": {
        "x": 0,
        "y": 0,
        "z": 0
      },
      "ModelWorldRotation": {
        "x": 0.0,
        "y": 41.36733,
        "z": 0.0
      }
    },
    {
      "Frame": 304,
      "FocusedName": "Fropp",
      "LocalPosition": {
        "x": 2.3090785313545603,
        "y": 0.6560055114907464,
        "z": -1.0017156621060634
      },
      "LocalRotation": {
        "x": -13.688673935051,
        "y": -74.65961392476302,
        "z": 0
      },
      "ModelWorldPosition": {
        "x": 0,
        "y": 0,
        "z": 0
      },
      "ModelWorldRotation": {
        "x": 0.0,
        "y": 41.36733,
        "z": 0.0
      }
    },
    {
      "Frame": 305,
      "FocusedName": "Fropp",
      "LocalPosition": {
        "x": 2.3153380694892918,
        "y": 0.6455167188398522,
        "z": -1.0380469373147772
      },
      "LocalRotation": {
        "x": -14.336142540659978,
        "y": -72.56254735461991,
        "z": 0
      },
      "ModelWorldPosition": {
        "x": 0,
        "y": 0,
        "z": 0
      },
      "ModelWorldRotation": {
        "x": 0.0,
        "y": 41.36733,
        "z": 0.0
      }
    },
    {
      "Frame": 306,
      "FocusedName": "Fropp",
      "LocalPosition": {
        "x": 2.328555837556563,
        "y": 0.6276154756145113,
        "z": -1.0638040597690674
      },
      "LocalRotation": {
        "x": -15.517644469622297,
        "y": -70.98609096670977,
        "z": 0
      },
      "ModelWorldPosition": {
        "x": 0,
        "y": 0,
        "z": 0
      },
      "ModelWorldRotation": {
        "x": 0.0,
        "y": 41.36733,
        "z": 0.0
      }
    },
    {
      "Frame": 307,
      "FocusedName": "Fropp",
      "LocalPosition": {
        "x": 2.3448713832463772,
        "y": 0.6040212451326096,
        "z": -1.0667280426204655
      },
      "LocalRotation": {
        "x": -17.149214555808285,
        "y": -70.25877061477128,
        "z": 0
      },
      "ModelWorldPosition": {
        "x": 0,
        "y": 0,
        "z": 0
      },
      "ModelWorldRotation": {
        "x": 0.0,
        "y": 41.36733,
        "z": 0.0
      }
    },
    {
      "Frame": 308,
      "FocusedName": "Fropp",
      "LocalPosition": {
        "x": 2.3554953145815745,
        "y": 0.5774808847156121,
        "z": -1.045271016849225
      },
      "LocalRotation": {
        "x": -19.096548122653317,
        "y": -70.28430727258846,
        "z": 0
      },
      "ModelWorldPosition": {
        "x": 0,
        "y": 0,
        "z": 0
      },
      "ModelWorldRotation": {
        "x": 0.0,
        "y": 41.36733,
        "z": 0.0
      }
    },
    {
      "Frame": 309,
      "FocusedName": "Fropp",
      "LocalPosition": {
        "x": 2.3513243259253267,
        "y": 0.5494361696613727,
        "z": -1.0073288367831608
      },
      "LocalRotation": {
        "x": -21.322400592400868,
        "y": -70.70594984361452,
        "z": 0
      },
      "ModelWorldPosition": {
        "x": 0,
        "y": 0,
        "z": 0
      },
      "ModelWorldRotation": {
        "x": 0.0,
        "y": 41.36733,
        "z": 0.0
      }
    },
    {
      "Frame": 310,
      "FocusedName": "Fropp",
      "LocalPosition": {
        "x": 2.328813430130635,
        "y": 0.52101678321289,
        "z": -0.9627191055977855
      },
      "LocalRotation": {
        "x": -23.7681455217095,
        "y": -71.19771433962839,
        "z": 0
      },
      "ModelWorldPosition": {
        "x": 0,
        "y": 0,
        "z": 0
      },
      "ModelWorldRotation": {
        "x": 0.0,
        "y": 41.36733,
        "z": 0.0
      }
    },
    {
      "Frame": 311,
      "FocusedName": "Fropp",
      "LocalPosition": {
        "x": 2.2922610140617214,
        "y": 0.493683699293318,
        "z": -0.9248073542942772
      },
      "LocalRotation": {
        "x": -26.244942992575062,
        "y": -71.3994003472856,
        "z": 0
      },
      "ModelWorldPosition": {
        "x": 0,
        "y": 0,
        "z": 0
      },
      "ModelWorldRotation": {
        "x": 0.0,
        "y": 41.36733,
        "z": 0.0
      }
    },
    {
      "Frame": 312,
      "FocusedName": "Fropp",
      "LocalPosition": {
        "x": 2.2561861318139917,
        "y": 0.4679780581133619,
        "z": -0.9165441184659006
      },
      "LocalRotation": {
        "x": -28.405348498710637,
        "y": -70.75179507223038,
        "z": 0
      },
      "ModelWorldPosition": {
        "x": 0,
        "y": 0,
        "z": 0
      },
      "ModelWorldRotation": {
        "x": 0.0,
        "y": 41.36733,
        "z": 0.0
      }
    },
    {
      "Frame": 313,
      "FocusedName": "Fropp",
      "LocalPosition": {
        "x": 2.238346610405844,
        "y": 0.4436252733991559,
        "z": -0.9525623482792567
      },
      "LocalRotation": {
        "x": -29.866392195220797,
        "y": -69.01930188210399,
        "z": 0
      },
      "ModelWorldPosition": {
        "x": 0,
        "y": 0,
        "z": 0
      },
      "ModelWorldRotation": {
        "x": 0.0,
        "y": 41.36733,
        "z": 0.0
      }
    },
    {
      "Frame": 314,
      "FocusedName": "Fropp",
      "LocalPosition": {
        "x": 2.264000394873666,
        "y": 0.4207475880512943,
        "z": -1.0322750631702746
      },
      "LocalRotation": {
        "x": -30.21258393831699,
        "y": -66.59711825863883,
        "z": 0
      },
      "ModelWorldPosition": {
        "x": 0,
        "y": 0,
        "z": 0
      },
      "ModelWorldRotation": {
        "x": 0.0,
        "y": 41.36733,
        "z": 0.0
      }
    },
    {
      "Frame": 315,
      "FocusedName": "Fropp",
      "LocalPosition": {
        "x": 2.35282479179351,
        "y": 0.40236904661757467,
        "z": -1.1281120856950795
      },
      "LocalRotation": {
        "x": -29.330299123134026,
        "y": -64.54664105135045,
        "z": 0
      },
      "ModelWorldPosition": {
        "x": 0,
        "y": 0,
        "z": 0
      },
      "ModelWorldRotation": {
        "x": 0.0,
        "y": 41.36733,
        "z": 0.0
      }
    },
    {
      "Frame": 316,
      "FocusedName": "Fropp",
      "LocalPosition": {
        "x": 2.535848989339383,
        "y": 0.39474244291987715,
        "z": -1.2126553326336604
      },
      "LocalRotation": {
        "x": -27.0917346369542,
        "y": -63.741032231104306,
        "z": 0
      },
      "ModelWorldPosition": {
        "x": 0,
        "y": 0,
        "z": 0
      },
      "ModelWorldRotation": {
        "x": 0.0,
        "y": 41.36733,
        "z": 0.0
      }
    },
    {
      "Frame": 317,
      "FocusedName": "Fropp",
      "LocalPosition": {
        "x": 2.7182364750175236,
        "y": 0.4073079095649186,
        "z": -1.2829656645580991
      },
      "LocalRotation": {
        "x": -24.309768933100912,
        "y": -63.09811854611094,
        "z": 0
      },
      "ModelWorldPosition": {
        "x": 0,
        "y": 0,
        "z": 0
      },
      "ModelWorldRotation": {
        "x": 0.0,
        "y": 41.36733,
        "z": 0.0
      }
    },
    {
      "Frame": 318,
      "FocusedName": "Fropp",
      "LocalPosition": {
        "x": 2.848840659762903,
        "y": 0.42772919741942017,
        "z": -1.289367993930087
      },
      "LocalRotation": {
        "x": -22.127313577393366,
        "y": -63.27203987633376,
        "z": 0
      },
      "ModelWorldPosition": {
        "x": 0,
        "y": 0,
        "z": 0
      },
      "ModelWorldRotation": {
        "x": 0.0,
        "y": 41.36733,
        "z": 0.0
      }
    },
    {
      "Frame": 319,
      "FocusedName": "Fropp",
      "LocalPosition": {
        "x": 2.938808388161871,
        "y": 0.4517756679099547,
        "z": -1.252691056186254
      },
      "LocalRotation": {
        "x": -20.319624119548735,
        "y": -63.91079772315381,
        "z": 0
      },
      "ModelWorldPosition": {
        "x": 0,
        "y": 0,
        "z": 0
      },
      "ModelWorldRotation": {
        "x": 0.0,
        "y": 41.36733,
        "z": 0.0
      }
    },
    {
      "Frame": 320,
      "FocusedName": "Fropp",
      "LocalPosition": {
        "x": 2.9862020475369473,
        "y": 0.4758720931627989,
        "z": -1.2030833838602155
      },
      "LocalRotation": {
        "x": -18.84353217002213,
        "y": -64.44602925439838,
        "z": 0
      },
      "ModelWorldPosition": {
        "x": 0,
        "y": 0,
        "z": 0
      },
      "ModelWorldRotation": {
        "x": 0.0,
        "y": 41.36733,
        "z": 0.0
      }
    },
    {
      "Frame": 321,
      "FocusedName": "Fropp",
      "LocalPosition": {
        "x": 2.9980826238974485,
        "y": 0.49864571343428543,
        "z": -1.1731761620090453
      },
      "LocalRotation": {
        "x": -17.57233305037684,
        "y": -64.32114055476393,
        "z": 0
      },
      "ModelWorldPosition": {
        "x": 0,
        "y": 0,
        "z": 0
      },
      "ModelWorldRotation": {
        "x": 0.0,
        "y": 41.36733,
        "z": 0.0
      }
    },
    {
      "Frame": 322,
      "FocusedName": "Fropp",
      "LocalPosition": {
        "x": 2.9850795969089363,
        "y": 0.5221843039104404,
        "z": -1.1728522361934242
      },
      "LocalRotation": {
        "x": -16.28991040283117,
        "y": -63.404127248897545,
        "z": 0
      },
      "ModelWorldPosition": {
        "x": 0,
        "y": 0,
        "z": 0
      },
      "ModelWorldRotation": {
        "x": 0.0,
        "y": 41.36733,
        "z": 0.0
      }
    },
    {
      "Frame": 323,
      "FocusedName": "Fropp",
      "LocalPosition": {
        "x": 2.9625183171210216,
        "y": 0.5451848967315944,
        "z": -1.210713984140569
      },
      "LocalRotation": {
        "x": -14.954774683637993,
        "y": -61.669422133130396,
        "z": 0
      },
      "ModelWorldPosition": {
        "x": 0,
        "y": 0,
        "z": 0
      },
      "ModelWorldRotation": {
        "x": 0.0,
        "y": 41.36733,
        "z": 0.0
      }
    },
    {
      "Frame": 324,
      "FocusedName": "Fropp",
      "LocalPosition": {
        "x": 2.9268397994528677,
        "y": 0.5681631732659367,
        "z": -1.2807960564504648
      },
      "LocalRotation": {
        "x": -13.57961280186855,
        "y": -59.20958511215821,
        "z": 0
      },
      "ModelWorldPosition": {
        "x": 0,
        "y": 0,
        "z": 0
      },
      "ModelWorldRotation": {
        "x": 0.0,
        "y": 41.36733,
        "z": 0.0
      }
    },
    {
      "Frame": 325,
      "FocusedName": "Fropp",
      "LocalPosition": {
        "x": 2.879777002819337,
        "y": 0.5916362497347515,
        "z": -1.3287688924309873
      },
      "LocalRotation": {
        "x": -12.273337459423956,
        "y": -57.06239167950904,
        "z": 0
      },
      "ModelWorldPosition": {
        "x": 0,
        "y": 0,
        "z": 0
      },
      "ModelWorldRotation": {
        "x": 0.0,
        "y": 41.36733,
        "z": 0.0
      }
    },
    {
      "Frame": 326,
      "FocusedName": "Fropp",
      "LocalPosition": {
        "x": 2.828466827379981,
        "y": 0.6114588263486037,
        "z": -1.3468649639497807
      },
      "LocalRotation": {
        "x": -11.248080045268694,
        "y": -55.4397358376176,
        "z": 0
      },
      "ModelWorldPosition": {
        "x": 0,
        "y": 0,
        "z": 0
      },
      "ModelWorldRotation": {
        "x": 0.0,
        "y": 41.36733,
        "z": 0.0
      }
    },
    {
      "Frame": 327,
      "FocusedName": "Fropp",
      "LocalPosition": {
        "x": 2.760900543557811,
        "y": 0.6271600562064837,
        "z": -1.357934793055131
      },
      "LocalRotation": {
        "x": -10.507551944514745,
        "y": -53.74726114704582,
        "z": 0
      },
      "ModelWorldPosition": {
        "x": 0,
        "y": 0,
        "z": 0
      },
      "ModelWorldRotation": {
        "x": 0.0,
        "y": 41.36733,
        "z": 0.0
      }
    },
    {
      "Frame": 328,
      "FocusedName": "Fropp",
      "LocalPosition": {
        "x": 2.6731659737759315,
        "y": 0.6379514934790154,
        "z": -1.358947877456373
      },
      "LocalRotation": {
        "x": -10.10843840104151,
        "y": -51.94814903986612,
        "z": 0
      },
      "ModelWorldPosition": {
        "x": 0,
        "y": 0,
        "z": 0
      },
      "ModelWorldRotation": {
        "x": 0.0,
        "y": 41.36733,
        "z": 0.0
      }
    },
    {
      "Frame": 329,
      "FocusedName": "Fropp",
      "LocalPosition": {
        "x": 2.5633678274493383,
        "y": 0.6443283527120305,
        "z": -1.3473345611839571
      },
      "LocalRotation": {
        "x": -10.039399323696585,
        "y": -50.003829128460964,
        "z": 0
      },
      "ModelWorldPosition": {
        "x": 0,
        "y": 0,
        "z": 0
      },
      "ModelWorldRotation": {
        "x": 0.0,
        "y": 41.36733,
        "z": 0.0
      }
    },
    {
      "Frame": 330,
      "FocusedName": "Fropp",
      "LocalPosition": {
        "x": 2.4459488146870085,
        "y": 0.6453616077729264,
        "z": -1.3148424797690796
      },
      "LocalRotation": {
        "x": -10.355279501218789,
        "y": -48.23348107351395,
        "z": 0
      },
      "ModelWorldPosition": {
        "x": 0,
        "y": 0,
        "z": 0
      },
      "ModelWorldRotation": {
        "x": 0.0,
        "y": 41.36733,
        "z": 0.0
      }
    },
    {
      "Frame": 331,
      "FocusedName": "Fropp",
      "LocalPosition": {
        "x": 2.347819755775216,
        "y": 0.6411851085253436,
        "z": -1.2613934443484267
      },
      "LocalRotation": {
        "x": -11.007703349803151,
        "y": -47.082702390981176,
        "z": 0
      },
      "ModelWorldPosition": {
        "x": 0,
        "y": 0,
        "z": 0
      },
      "ModelWorldRotation": {
        "x": 0.0,
        "y": 41.36733,
        "z": 0.0
      }
    },
    {
      "Frame": 332,
      "FocusedName": "Fropp",
      "LocalPosition": {
        "x": 2.2907080022749344,
        "y": 0.6345773072164808,
        "z": -1.2092878803966596
      },
      "LocalRotation": {
        "x": -11.700788223827743,
        "y": -46.56569513996654,
        "z": 0
      },
      "ModelWorldPosition": {
        "x": 0,
        "y": 0,
        "z": 0
      },
      "ModelWorldRotation": {
        "x": 0.0,
        "y": 41.36733,
        "z": 0.0
      }
    },
    {
      "Frame": 333,
      "FocusedName": "Fropp",
      "LocalPosition": {
        "x": 2.267994080779341,
        "y": 0.6270841662715452,
        "z": -1.1667433997359693
      },
      "LocalRotation": {
        "x": -12.309512267431217,
        "y": -46.4625604174574,
        "z": 0
      },
      "ModelWorldPosition": {
        "x": 0,
        "y": 0,
        "z": 0
      },
      "ModelWorldRotation": {
        "x": 0.0,
        "y": 41.36733,
        "z": 0.0
      }
    },
    {
      "Frame": 334,
      "FocusedName": "Fropp",
      "LocalPosition": {
        "x": 2.2698273850562876,
        "y": 0.6227694842504703,
        "z": -1.1403819200269767
      },
      "LocalRotation": {
        "x": -12.560271633153363,
        "y": -46.44849757934955,
        "z": 0
      },
      "ModelWorldPosition": {
        "x": 0,
        "y": 0,
        "z": 0
      },
      "ModelWorldRotation": {
        "x": 0.0,
        "y": 41.36733,
        "z": 0.0
      }
    },
    {
      "Frame": 335,
      "FocusedName": "Fropp",
      "LocalPosition": {
        "x": 2.2816571438839275,
        "y": 0.6220146029005443,
        "z": -1.1241163394502156
      },
      "LocalRotation": {
        "x": -12.50238159164985,
        "y": -46.37996307324654,
        "z": 0
      },
      "ModelWorldPosition": {
        "x": 0,
        "y": 0,
        "z": 0
      },
      "ModelWorldRotation": {
        "x": 0.0,
        "y": 41.36733,
        "z": 0.0
      }
    },
    {
      "Frame": 336,
      "FocusedName": "Fropp",
      "LocalPosition": {
        "x": 2.2949532743048433,
        "y": 0.624230639604342,
        "z": -1.1117682134039208
      },
      "LocalRotation": {
        "x": -12.237304993253431,
        "y": -46.23536899612254,
        "z": 0
      },
      "ModelWorldPosition": {
        "x": 0,
        "y": 0,
        "z": 0
      },
      "ModelWorldRotation": {
        "x": 0.0,
        "y": 41.36733,
        "z": 0.0
      }
    },
    {
      "Frame": 337,
      "FocusedName": "Fropp",
      "LocalPosition": {
        "x": 2.306658879004675,
        "y": 0.629363409477303,
        "z": -1.0991983526648244
      },
      "LocalRotation": {
        "x": -11.80237499889678,
        "y": -46.04485376919091,
        "z": 0
      },
      "ModelWorldPosition": {
        "x": 0,
        "y": 0,
        "z": 0
      },
      "ModelWorldRotation": {
        "x": 0.0,
        "y": 41.36733,
        "z": 0.0
      }
    },
    {
      "Frame": 338,
      "FocusedName": "Fropp",
      "LocalPosition": {
        "x": 2.3130176810610625,
        "y": 0.635062149476237,
        "z": -1.085054550768412
      },
      "LocalRotation": {
        "x": -11.365231386560538,
        "y": -45.79450897733379,
        "z": 0
      },
      "ModelWorldPosition": {
        "x": 0,
        "y": 0,
        "z": 0
      },
      "ModelWorldRotation": {
        "x": 0.0,
        "y": 41.36733,
        "z": 0.0
      }
    },
    {
      "Frame": 339,
      "FocusedName": "Fropp",
      "LocalPosition": {
        "x": 2.3147201235404053,
        "y": 0.6405168012014557,
        "z": -1.0680758938313424
      },
      "LocalRotation": {
        "x": -10.975110911232534,
        "y": -45.524841734712105,
        "z": 0
      },
      "ModelWorldPosition": {
        "x": 0,
        "y": 0,
        "z": 0
      },
      "ModelWorldRotation": {
        "x": 0.0,
        "y": 41.36733,
        "z": 0.0
      }
    },
    {
      "Frame": 340,
      "FocusedName": "Fropp",
      "LocalPosition": {
        "x": 2.3126924586039292,
        "y": 0.6452065300797856,
        "z": -1.0498602567030495
      },
      "LocalRotation": {
        "x": -10.652113964554914,
        "y": -45.22457241074497,
        "z": 0
      },
      "ModelWorldPosition": {
        "x": 0,
        "y": 0,
        "z": 0
      },
      "ModelWorldRotation": {
        "x": 0.0,
        "y": 41.36733,
        "z": 0.0
      }
    },
    {
      "Frame": 341,
      "FocusedName": "Fropp",
      "LocalPosition": {
        "x": 2.3031589052402976,
        "y": 0.6484175470533887,
        "z": -1.0285858471943676
      },
      "LocalRotation": {
        "x": -10.454938847041362,
        "y": -44.863915787150496,
        "z": 0
      },
      "ModelWorldPosition": {
        "x": 0,
        "y": 0,
        "z": 0
      },
      "ModelWorldRotation": {
        "x": 0.0,
        "y": 41.36733,
        "z": 0.0
      }
    },
    {
      "Frame": 342,
      "FocusedName": "Fropp",
      "LocalPosition": {
        "x": 2.2947846476203,
        "y": 0.6510947967297676,
        "z": -1.0061092422208182
      },
      "LocalRotation": {
        "x": -10.290544614189784,
        "y": -44.54877264672667,
        "z": 0
      },
      "ModelWorldPosition": {
        "x": 0,
        "y": 0,
        "z": 0
      },
      "ModelWorldRotation": {
        "x": 0.0,
        "y": 41.36733,
        "z": 0.0
      }
    },
    {
      "Frame": 343,
      "FocusedName": "Fropp",
      "LocalPosition": {
        "x": 2.285307929606873,
        "y": 0.653415621628598,
        "z": -0.9826434799262881
      },
      "LocalRotation": {
        "x": -10.154318014718697,
        "y": -44.23462306156208,
        "z": 0
      },
      "ModelWorldPosition": {
        "x": 0,
        "y": 0,
        "z": 0
      },
      "ModelWorldRotation": {
        "x": 0.0,
        "y": 41.36733,
        "z": 0.0
      }
    },
    {
      "Frame": 344,
      "FocusedName": "Fropp",
      "LocalPosition": {
        "x": 2.2766526984076267,
        "y": 0.6550365385166265,
        "z": -0.9605277502651488
      },
      "LocalRotation": {
        "x": -10.053492393199534,
        "y": -43.91603970397085,
        "z": 0
      },
      "ModelWorldPosition": {
        "x": 0,
        "y": 0,
        "z": 0
      },
      "ModelWorldRotation": {
        "x": 0.0,
        "y": 41.36733,
        "z": 0.0
      }
    },
    {
      "Frame": 345,
      "FocusedName": "Fropp",
      "LocalPosition": {
        "x": 2.274999217789137,
        "y": 0.6561889641498341,
        "z": -0.9489666125515681
      },
      "LocalRotation": {
        "x": -9.926725432772798,
        "y": -43.54168567003439,
        "z": 0
      },
      "ModelWorldPosition": {
        "x": 0,
        "y": 0,
        "z": 0
      },
      "ModelWorldRotation": {
        "x": 0.0,
        "y": 41.36733,
        "z": 0.0
      }
    },
    {
      "Frame": 346,
      "FocusedName": "Fropp",
      "LocalPosition": {
        "x": 2.27845874656364,
        "y": 0.6568970151078503,
        "z": -0.946194811347456
      },
      "LocalRotation": {
        "x": -9.785629881471152,
        "y": -43.1151768438193,
        "z": 0
      },
      "ModelWorldPosition": {
        "x": 0,
        "y": 0,
        "z": 0
      },
      "ModelWorldRotation": {
        "x": 0.0,
        "y": 41.36733,
        "z": 0.0
      }
    },
    {
      "Frame": 347,
      "FocusedName": "Fropp",
      "LocalPosition": {
        "x": 2.282854695204368,
        "y": 0.6569757213728228,
        "z": -0.9476970199958116
      },
      "LocalRotation": {
        "x": -9.668224144852374,
        "y": -42.64668693803728,
        "z": 0
      },
      "ModelWorldPosition": {
        "x": 0,
        "y": 0,
        "z": 0
      },
      "ModelWorldRotation": {
        "x": 0.0,
        "y": 41.36733,
        "z": 0.0
      }
    },
    {
      "Frame": 348,
      "FocusedName": "Fropp",
      "LocalPosition": {
        "x": 2.2869114965794237,
        "y": 0.6565560143565701,
        "z": -0.9496296726746388
      },
      "LocalRotation": {
        "x": -9.581473945705199,
        "y": -42.1792455688123,
        "z": 0
      },
      "ModelWorldPosition": {
        "x": 0,
        "y": 0,
        "z": 0
      },
      "ModelWorldRotation": {
        "x": 0.0,
        "y": 41.36733,
        "z": 0.0
      }
    },
    {
      "Frame": 349,
      "FocusedName": "Fropp",
      "LocalPosition": {
        "x": 2.2932545998082134,
        "y": 0.6559530947432054,
        "z": -0.954701527771265
      },
      "LocalRotation": {
        "x": -9.491398892270652,
        "y": -41.71322431283125,
        "z": 0
      },
      "ModelWorldPosition": {
        "x": 0,
        "y": 0,
        "z": 0
      },
      "ModelWorldRotation": {
        "x": 0.0,
        "y": 41.36733,
        "z": 0.0
      }
    },
    {
      "Frame": 350,
      "FocusedName": "Fropp",
      "LocalPosition": {
        "x": 2.3003147542959095,
        "y": 0.6552197564858366,
        "z": -0.9654169940581082
      },
      "LocalRotation": {
        "x": -9.392155967374222,
        "y": -41.184852822983295,
        "z": 0
      },
      "ModelWorldPosition": {
        "x": 0,
        "y": 0,
        "z": 0
      },
      "ModelWorldRotation": {
        "x": 0.0,
        "y": 41.36733,
        "z": 0.0
      }
    },
    {
      "Frame": 351,
      "FocusedName": "Fropp",
      "LocalPosition": {
        "x": 2.3086579443598665,
        "y": 0.6549318516316708,
        "z": -0.977771628312844
      },
      "LocalRotation": {
        "x": -9.26245989956945,
        "y": -40.66610262052967,
        "z": 0
      },
      "ModelWorldPosition": {
        "x": 0,
        "y": 0,
        "z": 0
      },
      "ModelWorldRotation": {
        "x": 0.0,
        "y": 41.36733,
        "z": 0.0
      }
    },
    {
      "Frame": 352,
      "FocusedName": "Fropp",
      "LocalPosition": {
        "x": 2.3086579443598665,
        "y": 0.6549318516316708,
        "z": -0.977771628312844
      },
      "LocalRotation": {
        "x": -9.17412038172428,
        "y": -40.202288886899254,
        "z": 0
      },
      "ModelWorldPosition": {
        "x": 0,
        "y": 0,
        "z": 0
      },
      "ModelWorldRotation": {
        "x": 0.0,
        "y": 41.36733,
        "z": 0.0
      }
    }
  ]
}