{
  "data": [
    {
      "Frame": 301,
      "FocusedName": "Fropp",
      "LocalPosition": {
        "x": 2.7958448911810527,
        "y": 0.1,
        "z": 1.2531178838342438
      },
      "LocalRotation": {
        "x": -22.617834318894538,
        "y": -105.78248986068397,
        "z": 0
      },
      "ModelWorldPosition": {
        "x": 0,
        "y": 0,
        "z": 0
      },
      "ModelWorldRotation": {
        "x": 0.0,
        "y": 41.36733,
        "z": 0.0
      }
    },
    {
      "Frame": 302,
      "FocusedName": "Fropp",
      "LocalPosition": {
        "x": 2.8041368718667323,
        "y": 0.1,
        "z": 1.2410856155562746
      },
      "LocalRotation": {
        "x": -22.746678285361227,
        "y": -103.06483243487247,
        "z": 0
      },
      "ModelWorldPosition": {
        "x": 0,
        "y": 0,
        "z": 0
      },
      "ModelWorldRotation": {
        "x": 0.0,
        "y": 41.36733,
        "z": 0.0
      }
    },
    {
      "Frame": 303,
      "FocusedName": "Fropp",
      "LocalPosition": {
        "x": 2.7861121988729165,
        "y": 0.1,
        "z": 1.2538722234531288
      },
      "LocalRotation": {
        "x": -23.21805621687183,
        "y": -101.85640608864114,
        "z": 0
      },
      "ModelWorldPosition": {
        "x": 0,
        "y": 0,
        "z": 0
      },
      "ModelWorldRotation": {
        "x": 0.0,
        "y": 41.36733,
        "z": 0.0
      }
    },
    {
      "Frame": 304,
      "FocusedName": "Fropp",
      "LocalPosition": {
        "x": 2.793764983195433,
        "y": 0.1,
        "z": 1.2420579200505568
      },
      "LocalRotation": {
        "x": -23.275690261831457,
        "y": -99.23055741713588,
        "z": 0
      },
      "ModelWorldPosition": {
        "x": 0,
        "y": 0,
        "z": 0
      },
      "ModelWorldRotation": {
        "x": 0.0,
        "y": 41.36733,
        "z": 0.0
      }
    },
    {
      "Frame": 305,
      "FocusedName": "Fropp",
      "LocalPosition": {
        "x": 2.818264441940749,
        "y": 0.1,
        "z": 1.225271606040086
      },
      "LocalRotation": {
        "x": -22.9289487607966,
        "y": -96.28729032709782,
        "z": 0
      },
      "ModelWorldPosition": {
        "x": 0,
        "y": 0,
        "z": 0
      },
      "ModelWorldRotation": {
        "x": 0.0,
        "y": 41.36733,
        "z": 0.0
      }
    },
    {
      "Frame": 306,
      "FocusedName": "Fropp",
      "LocalPosition": {
        "x": 2.8579188505155613,
        "y": 0.19694424228577145,
        "z": 1.2133709187385795
      },
      "LocalRotation": {
        "x": -22.09965115507606,
        "y": -93.5740192655692,
        "z": 0
      },
      "ModelWorldPosition": {
        "x": 0,
        "y": 0,
        "z": 0
      },
      "ModelWorldRotation": {
        "x": 0.0,
        "y": 41.36733,
        "z": 0.0
      }
    },
    {
      "Frame": 307,
      "FocusedName": "Fropp",
      "LocalPosition": {
        "x": 2.9025760783884023,
        "y": 0.35771050782527913,
        "z": 1.2120199368635192
      },
      "LocalRotation": {
        "x": -20.90295794717447,
        "y": -91.41901565949016,
        "z": 0
      },
      "ModelWorldPosition": {
        "x": 0,
        "y": 0,
        "z": 0
      },
      "ModelWorldRotation": {
        "x": 0.0,
        "y": 41.36733,
        "z": 0.0
      }
    },
    {
      "Frame": 308,
      "FocusedName": "Fropp",
      "LocalPosition": {
        "x": 2.9384714951522333,
        "y": 0.5461494527691884,
        "z": 1.2219338297906912
      },
      "LocalRotation": {
        "x": -19.568460756212986,
        "y": -89.85855695627068,
        "z": 0
      },
      "ModelWorldPosition": {
        "x": 0,
        "y": 0,
        "z": 0
      },
      "ModelWorldRotation": {
        "x": 0.0,
        "y": 41.36733,
        "z": 0.0
      }
    },
    {
      "Frame": 309,
      "FocusedName": "Fropp",
      "LocalPosition": {
        "x": 2.955688795271129,
        "y": 0.7514002584644104,
        "z": 1.2394644379284983
      },
      "LocalRotation": {
        "x": -18.258307571099692,
        "y": -88.68051827936021,
        "z": 0
      },
      "ModelWorldPosition": {
        "x": 0,
        "y": 0,
        "z": 0
      },
      "ModelWorldRotation": {
        "x": 0.0,
        "y": 41.36733,
        "z": 0.0
      }
    },
    {
      "Frame": 310,
      "FocusedName": "Fropp",
      "LocalPosition": {
        "x": 2.9495852301061998,
        "y": 0.962362084172311,
        "z": 1.2600756868125123
      },
      "LocalRotation": {
        "x": -17.06542658767343,
        "y": -87.62409780174187,
        "z": 0
      },
      "ModelWorldPosition": {
        "x": 0,
        "y": 0,
        "z": 0
      },
      "ModelWorldRotation": {
        "x": 0.0,
        "y": 41.36733,
        "z": 0.0
      }
    },
    {
      "Frame": 311,
      "FocusedName": "Fropp",
      "LocalPosition": {
        "x": 2.9222943159204755,
        "y": 1.1644909340181724,
        "z": 1.2775922358026488
      },
      "LocalRotation": {
        "x": -16.03885267412842,
        "y": -86.34510789138542,
        "z": 0
      },
      "ModelWorldPosition": {
        "x": 0,
        "y": 0,
        "z": 0
      },
      "ModelWorldRotation": {
        "x": 0.0,
        "y": 41.36733,
        "z": 0.0
      }
    },
    {
      "Frame": 312,
      "FocusedName": "Fropp",
      "LocalPosition": {
        "x": 2.883234873034684,
        "y": 1.3508357517912897,
        "z": 1.281410138437799
      },
      "LocalRotation": {
        "x": -15.10435163761214,
        "y": -84.26427640823968,
        "z": 0
      },
      "ModelWorldPosition": {
        "x": 0,
        "y": 0,
        "z": 0
      },
      "ModelWorldRotation": {
        "x": 0.0,
        "y": 41.36733,
        "z": 0.0
      }
    },
    {
      "Frame": 313,
      "FocusedName": "Fropp",
      "LocalPosition": {
        "x": 2.8432546418561326,
        "y": 1.5216989269111574,
        "z": 1.2647684622985786
      },
      "LocalRotation": {
        "x": -14.12086061992241,
        "y": -81.03247977879997,
        "z": 0
      },
      "ModelWorldPosition": {
        "x": 0,
        "y": 0,
        "z": 0
      },
      "ModelWorldRotation": {
        "x": 0.0,
        "y": 41.36733,
        "z": 0.0
      }
    },
    {
      "Frame": 314,
      "FocusedName": "Fropp",
      "LocalPosition": {
        "x": 2.816835609137015,
        "y": 1.675590000656413,
        "z": 1.2279384128411666
      },
      "LocalRotation": {
        "x": -12.941880943242126,
        "y": -76.87771422203922,
        "z": 0
      },
      "ModelWorldPosition": {
        "x": 0,
        "y": 0,
        "z": 0
      },
      "ModelWorldRotation": {
        "x": 0.0,
        "y": 41.36733,
        "z": 0.0
      }
    },
    {
      "Frame": 315,
      "FocusedName": "Fropp",
      "LocalPosition": {
        "x": 2.821834914572789,
        "y": 1.7937978110808308,
        "z": 1.183658371893303
      },
      "LocalRotation": {
        "x": -11.65500967528395,
        "y": -72.93476990150802,
        "z": 0
      },
      "ModelWorldPosition": {
        "x": 0,
        "y": 0,
        "z": 0
      },
      "ModelWorldRotation": {
        "x": 0.0,
        "y": 41.36733,
        "z": 0.0
      }
    },
    {
      "Frame": 316,
      "FocusedName": "Fropp",
      "LocalPosition": {
        "x": 2.8901889599395822,
        "y": 1.8413203582589808,
        "z": 1.1445964484561806
      },
      "LocalRotation": {
        "x": -10.441717371276084,
        "y": -70.40139939072854,
        "z": 0
      },
      "ModelWorldPosition": {
        "x": 0,
        "y": 0,
        "z": 0
      },
      "ModelWorldRotation": {
        "x": 0.0,
        "y": 41.36733,
        "z": 0.0
      }
    },
    {
      "Frame": 317,
      "FocusedName": "Fropp",
      "LocalPosition": {
        "x": 3.0007840281748304,
        "y": 1.7625358998010707,
        "z": 1.112110627270884
      },
      "LocalRotation": {
        "x": -9.939713368913743,
        "y": -68.73602647687136,
        "z": 0
      },
      "ModelWorldPosition": {
        "x": 0,
        "y": 0,
        "z": 0
      },
      "ModelWorldRotation": {
        "x": 0.0,
        "y": 41.36733,
        "z": 0.0
      }
    },
    {
      "Frame": 318,
      "FocusedName": "Fropp",
      "LocalPosition": {
        "x": 3.0995443417563004,
        "y": 1.6293823829985041,
        "z": 1.1091525282055674
      },
      "LocalRotation": {
        "x": -9.981214670903626,
        "y": -68.13965946973775,
        "z": 0
      },
      "ModelWorldPosition": {
        "x": 0,
        "y": 0,
        "z": 0
      },
      "ModelWorldRotation": {
        "x": 0.0,
        "y": 41.36733,
        "z": 0.0
      }
    },
    {
      "Frame": 319,
      "FocusedName": "Fropp",
      "LocalPosition": {
        "x": 3.1785974297771062,
        "y": 1.4652495191809924,
        "z": 1.1260985503414163
      },
      "LocalRotation": {
        "x": -10.358637045826427,
        "y": -68.06431654658351,
        "z": 0
      },
      "ModelWorldPosition": {
        "x": 0,
        "y": 0,
        "z": 0
      },
      "ModelWorldRotation": {
        "x": 0.0,
        "y": 41.36733,
        "z": 0.0
      }
    },
    {
      "Frame": 320,
      "FocusedName": "Fropp",
      "LocalPosition": {
        "x": 3.2286612846659795,
        "y": 1.2941612652818084,
        "z": 1.1490190220344578
      },
      "LocalRotation": {
        "x": -10.926431584459536,
        "y": -67.90209615646087,
        "z": 0
      },
      "ModelWorldPosition": {
        "x": 0,
        "y": 0,
        "z": 0
      },
      "ModelWorldRotation": {
        "x": 0.0,
        "y": 41.36733,
        "z": 0.0
      }
    },
    {
      "Frame": 321,
      "FocusedName": "Fropp",
      "LocalPosition": {
        "x": 3.251343368793306,
        "y": 1.128011473551602,
        "z": 1.1628371997419709
      },
      "LocalRotation": {
        "x": -11.567292893682122,
        "y": -67.1653325457163,
        "z": 0
      },
      "ModelWorldPosition": {
        "x": 0,
        "y": 0,
        "z": 0
      },
      "ModelWorldRotation": {
        "x": 0.0,
        "y": 41.36733,
        "z": 0.0
      }
    },
    {
      "Frame": 322,
      "FocusedName": "Fropp",
      "LocalPosition": {
        "x": 3.252930978144306,
        "y": 0.953685705934818,
        "z": 1.162986864746182
      },
      "LocalRotation": {
        "x": -12.289685058550788,
        "y": -65.79150133727909,
        "z": 0
      },
      "ModelWorldPosition": {
        "x": 0,
        "y": 0,
        "z": 0
      },
      "ModelWorldRotation": {
        "x": 0.0,
        "y": 41.36733,
        "z": 0.0
      }
    },
    {
      "Frame": 323,
      "FocusedName": "Fropp",
      "LocalPosition": {
        "x": 3.2397045235330744,
        "y": 0.782859719879669,
        "z": 1.1454934190475392
      },
      "LocalRotation": {
        "x": -12.96103621942548,
        "y": -63.76002823846061,
        "z": 0
      },
      "ModelWorldPosition": {
        "x": 0,
        "y": 0,
        "z": 0
      },
      "ModelWorldRotation": {
        "x": 0.0,
        "y": 41.36733,
        "z": 0.0
      }
    },
    {
      "Frame": 324,
      "FocusedName": "Fropp",
      "LocalPosition": {
        "x": 3.210414962395556,
        "y": 0.6137972098225108,
        "z": 1.113113061750962
      },
      "LocalRotation": {
        "x": -13.58580315734855,
        "y": -61.16981416725559,
        "z": 0
      },
      "ModelWorldPosition": {
        "x": 0,
        "y": 0,
        "z": 0
      },
      "ModelWorldRotation": {
        "x": 0.0,
        "y": 41.36733,
        "z": 0.0
      }
    },
    {
      "Frame": 325,
      "FocusedName": "Fropp",
      "LocalPosition": {
        "x": 3.1656711998537586,
        "y": 0.44476915174274234,
        "z": 1.090947941365957
      },
      "LocalRotation": {
        "x": -14.25659521035989,
        "y": -58.8329300899481,
        "z": 0
      },
      "ModelWorldPosition": {
        "x": 0,
        "y": 0,
        "z": 0
      },
      "ModelWorldRotation": {
        "x": 0.0,
        "y": 41.36733,
        "z": 0.0
      }
    },
    {
      "Frame": 326,
      "FocusedName": "Fropp",
      "LocalPosition": {
        "x": 3.1152372725158695,
        "y": 0.3062692261793305,
        "z": 1.0825869263141776
      },
      "LocalRotation": {
        "x": -14.834570159290465,
        "y": -56.880850340366564,
        "z": 0
      },
      "ModelWorldPosition": {
        "x": 0,
        "y": 0,
        "z": 0
      },
      "ModelWorldRotation": {
        "x": 0.0,
        "y": 41.36733,
        "z": 0.0
      }
    },
    {
      "Frame": 327,
      "FocusedName": "Fropp",
      "LocalPosition": {
        "x": 3.058472568327358,
        "y": 0.19997776904084308,
        "z": 1.0774722798742393
      },
      "LocalRotation": {
        "x": -15.312007014200447,
        "y": -54.881033708599766,
        "z": 0
      },
      "ModelWorldPosition": {
        "x": 0,
        "y": 0,
        "z": 0
      },
      "ModelWorldRotation": {
        "x": 0.0,
        "y": 41.36733,
        "z": 0.0
      }
    },
    {
      "Frame": 328,
      "FocusedName": "Fropp",
      "LocalPosition": {
        "x": 2.9983024125448194,
        "y": 0.12888941810706012,
        "z": 1.0770041996105915
      },
      "LocalRotation": {
        "x": -15.702072509649,
        "y": -52.833784274880436,
        "z": 0
      },
      "ModelWorldPosition": {
        "x": 0,
        "y": 0,
        "z": 0
      },
      "ModelWorldRotation": {
        "x": 0.0,
        "y": 41.36733,
        "z": 0.0
      }
    },
    {
      "Frame": 329,
      "FocusedName": "Fropp",
      "LocalPosition": {
        "x": 2.935223155208627,
        "y": 0.1,
        "z": 1.0823699560430806
      },
      "LocalRotation": {
        "x": -16.048779353500294,
        "y": -50.7349195816624,
        "z": 0
      },
      "ModelWorldPosition": {
        "x": 0,
        "y": 0,
        "z": 0
      },
      "ModelWorldRotation": {
        "x": 0.0,
        "y": 41.36733,
        "z": 0.0
      }
    },
    {
      "Frame": 330,
      "FocusedName": "Fropp",
      "LocalPosition": {
        "x": 2.8789202715462796,
        "y": 0.1,
        "z": 1.0973824288602503
      },
      "LocalRotation": {
        "x": -16.31167805442918,
        "y": -48.817574906021946,
        "z": 0
      },
      "ModelWorldPosition": {
        "x": 0,
        "y": 0,
        "z": 0
      },
      "ModelWorldRotation": {
        "x": 0.0,
        "y": 41.36733,
        "z": 0.0
      }
    },
    {
      "Frame": 331,
      "FocusedName": "Fropp",
      "LocalPosition": {
        "x": 2.841786678764102,
        "y": 0.10791834672457856,
        "z": 1.1220777440390766
      },
      "LocalRotation": {
        "x": -16.409816141360935,
        "y": -47.35586554947209,
        "z": 0
      },
      "ModelWorldPosition": {
        "x": 0,
        "y": 0,
        "z": 0
      },
      "ModelWorldRotation": {
        "x": 0.0,
        "y": 41.36733,
        "z": 0.0
      }
    },
    {
      "Frame": 332,
      "FocusedName": "Fropp",
      "LocalPosition": {
        "x": 2.827906458109383,
        "y": 0.15093658685647382,
        "z": 1.1461523286266622
      },
      "LocalRotation": {
        "x": -16.27736252082191,
        "y": -46.306872024803496,
        "z": 0
      },
      "ModelWorldPosition": {
        "x": 0,
        "y": 0,
        "z": 0
      },
      "ModelWorldRotation": {
        "x": 0.0,
        "y": 41.36733,
        "z": 0.0
      }
    },
    {
      "Frame": 333,
      "FocusedName": "Fropp",
      "LocalPosition": {
        "x": 2.830864877516853,
        "y": 0.2004835489111232,
        "z": 1.1658093598671035
      },
      "LocalRotation": {
        "x": -15.960870250712418,
        "y": -45.515607057034224,
        "z": 0
      },
      "ModelWorldPosition": {
        "x": 0,
        "y": 0,
        "z": 0
      },
      "ModelWorldRotation": {
        "x": 0.0,
        "y": 41.36733,
        "z": 0.0
      }
    },
    {
      "Frame": 334,
      "FocusedName": "Fropp",
      "LocalPosition": {
        "x": 2.8390937865218557,
        "y": 0.22936993783491144,
        "z": 1.1779892812608252
      },
      "LocalRotation": {
        "x": -15.609427079133852,
        "y": -44.79868361505606,
        "z": 0
      },
      "ModelWorldPosition": {
        "x": 0,
        "y": 0,
        "z": 0
      },
      "ModelWorldRotation": {
        "x": 0.0,
        "y": 41.36733,
        "z": 0.0
      }
    },
    {
      "Frame": 335,
      "FocusedName": "Fropp",
      "LocalPosition": {
        "x": 2.8458230244327147,
        "y": 0.23444987899535996,
        "z": 1.1855045457693125
      },
      "LocalRotation": {
        "x": -15.311291293669754,
        "y": -44.08403970712876,
        "z": 0
      },
      "ModelWorldPosition": {
        "x": 0,
        "y": 0,
        "z": 0
      },
      "ModelWorldRotation": {
        "x": 0.0,
        "y": 41.36733,
        "z": 0.0
      }
    },
    {
      "Frame": 336,
      "FocusedName": "Fropp",
      "LocalPosition": {
        "x": 2.8482333891236324,
        "y": 0.21955908713947458,
        "z": 1.1912098098995478
      },
      "LocalRotation": {
        "x": -15.09382349037763,
        "y": -43.35773291415724,
        "z": 0
      },
      "ModelWorldPosition": {
        "x": 0,
        "y": 0,
        "z": 0
      },
      "ModelWorldRotation": {
        "x": 0.0,
        "y": 41.36733,
        "z": 0.0
      }
    },
    {
      "Frame": 337,
      "FocusedName": "Fropp",
      "LocalPosition": {
        "x": 2.844721262685596,
        "y": 0.18532827056169054,
        "z": 1.1970175231774938
      },
      "LocalRotation": {
        "x": -14.971076873878985,
        "y": -42.63200749093345,
        "z": 0
      },
      "ModelWorldPosition": {
        "x": 0,
        "y": 0,
        "z": 0
      },
      "ModelWorldRotation": {
        "x": 0.0,
        "y": 41.36733,
        "z": 0.0
      }
    },
    {
      "Frame": 338,
      "FocusedName": "Fropp",
      "LocalPosition": {
        "x": 2.837316780450708,
        "y": 0.14775836490868288,
        "z": 1.2035524520664787
      },
      "LocalRotation": {
        "x": -14.882490505033928,
        "y": -41.88440497613235,
        "z": 0
      },
      "ModelWorldPosition": {
        "x": 0,
        "y": 0,
        "z": 0
      },
      "ModelWorldRotation": {
        "x": 0.0,
        "y": 41.36733,
        "z": 0.0
      }
    },
    {
      "Frame": 339,
      "FocusedName": "Fropp",
      "LocalPosition": {
        "x": 2.8277851915953405,
        "y": 0.11223977758272019,
        "z": 1.211397182678999
      },
      "LocalRotation": {
        "x": -14.805116611868982,
        "y": -41.1367249625193,
        "z": 0
      },
      "ModelWorldPosition": {
        "x": 0,
        "y": 0,
        "z": 0
      },
      "ModelWorldRotation": {
        "x": 0.0,
        "y": 41.36733,
        "z": 0.0
      }
    },
    {
      "Frame": 340,
      "FocusedName": "Fropp",
      "LocalPosition": {
        "x": 2.8176599367447643,
        "y": 0.1,
        "z": 1.2198134412050137
      },
      "LocalRotation": {
        "x": -14.717562564492823,
        "y": -40.38350945427973,
        "z": 0
      },
      "ModelWorldPosition": {
        "x": 0,
        "y": 0,
        "z": 0
      },
      "ModelWorldRotation": {
        "x": 0.0,
        "y": 41.36733,
        "z": 0.0
      }
    },
    {
      "Frame": 341,
      "FocusedName": "Fropp",
      "LocalPosition": {
        "x": 2.806799378117671,
        "y": 0.1,
        "z": 1.2296429590611453
      },
      "LocalRotation": {
        "x": -14.617107698262501,
        "y": -39.605459039416225,
        "z": 0
      },
      "ModelWorldPosition": {
        "x": 0,
        "y": 0,
        "z": 0
      },
      "ModelWorldRotation": {
        "x": 0.0,
        "y": 41.36733,
        "z": 0.0
      }
    },
    {
      "Frame": 342,
      "FocusedName": "Fropp",
      "LocalPosition": {
        "x": 2.7974476554171255,
        "y": 0.1,
        "z": 1.2400279330761732
      },
      "LocalRotation": {
        "x": -14.503175976518094,
        "y": -38.87185233452469,
        "z": 0
      },
      "ModelWorldPosition": {
        "x": 0,
        "y": 0,
        "z": 0
      },
      "ModelWorldRotation": {
        "x": 0.0,
        "y": 41.36733,
        "z": 0.0
      }
    },
    {
      "Frame": 343,
      "FocusedName": "Fropp",
      "LocalPosition": {
        "x": 2.788244226355778,
        "y": 0.1,
        "z": 1.2508699322107528
      },
      "LocalRotation": {
        "x": -14.385613981604237,
        "y": -38.15445125301095,
        "z": 0
      },
      "ModelWorldPosition": {
        "x": 0,
        "y": 0,
        "z": 0
      },
      "ModelWorldRotation": {
        "x": 0.0,
        "y": 41.36733,
        "z": 0.0
      }
    },
    {
      "Frame": 344,
      "FocusedName": "Fropp",
      "LocalPosition": {
        "x": 2.780836218227959,
        "y": 0.1,
        "z": 1.2610881692676654
      },
      "LocalRotation": {
        "x": -14.245747074389968,
        "y": -37.45404923852945,
        "z": 0
      },
      "ModelWorldPosition": {
        "x": 0,
        "y": 0,
        "z": 0
      },
      "ModelWorldRotation": {
        "x": 0.0,
        "y": 41.36733,
        "z": 0.0
      }
    },
    {
      "Frame": 345,
      "FocusedName": "Fropp",
      "LocalPosition": {
        "x": 2.7776291721953834,
        "y": 0.1,
        "z": 1.2664298173893895
      },
      "LocalRotation": {
        "x": -14.051460874112223,
        "y": -36.755788567819934,
        "z": 0
      },
      "ModelWorldPosition": {
        "x": 0,
        "y": 0,
        "z": 0
      },
      "ModelWorldRotation": {
        "x": 0.0,
        "y": 41.36733,
        "z": 0.0
      }
    },
    {
      "Frame": 346,
      "FocusedName": "Fropp",
      "LocalPosition": {
        "x": 2.7777186377247216,
        "y": 0.1,
        "z": 1.2677104860452384
      },
      "LocalRotation": {
        "x": -13.816398989823895,
        "y": -36.061041524220975,
        "z": 0
      },
      "ModelWorldPosition": {
        "x": 0,
        "y": 0,
        "z": 0
      },
      "ModelWorldRotation": {
        "x": 0.0,
        "y": 41.36733,
        "z": 0.0
      }
    },
    {
      "Frame": 347,
      "FocusedName": "Fropp",
      "LocalPosition": {
        "x": 2.779581613820067,
        "y": 0.1,
        "z": 1.2670164133506887
      },
      "LocalRotation": {
        "x": -13.560319336314507,
        "y": -35.369091019636144,
        "z": 0
      },
      "ModelWorldPosition": {
        "x": 0,
        "y": 0,
        "z": 0
      },
      "ModelWorldRotation": {
        "x": 0.0,
        "y": 41.36733,
        "z": 0.0
      }
    },
    {
      "Frame": 348,
      "FocusedName": "Fropp",
      "LocalPosition": {
        "x": 2.782351574164215,
        "y": 0.1,
        "z": 1.2661234605282623
      },
      "LocalRotation": {
        "x": -13.300436449788393,
        "y": -34.698144070627826,
        "z": 0
      },
      "ModelWorldPosition": {
        "x": 0,
        "y": 0,
        "z": 0
      },
      "ModelWorldRotation": {
        "x": 0.0,
        "y": 41.36733,
        "z": 0.0
      }
    },
    {
      "Frame": 349,
      "FocusedName": "Fropp",
      "LocalPosition": {
        "x": 2.7865651284716364,
        "y": 0.1,
        "z": 1.2637800868982842
      },
      "LocalRotation": {
        "x": -13.032708021113464,
        "y": -34.05196762548231,
        "z": 0
      },
      "ModelWorldPosition": {
        "x": 0,
        "y": 0,
        "z": 0
      },
      "ModelWorldRotation": {
        "x": 0.0,
        "y": 41.36733,
        "z": 0.0
      }
    },
    {
      "Frame": 350,
      "FocusedName": "Fropp",
      "LocalPosition": {
        "x": 2.7913815722805366,
        "y": 0.1,
        "z": 1.2588291684175474
      },
      "LocalRotation": {
        "x": -12.75569964852356,
        "y": -33.39683378069181,
        "z": 0
      },
      "ModelWorldPosition": {
        "x": 0,
        "y": 0,
        "z": 0
      },
      "ModelWorldRotation": {
        "x": 0.0,
        "y": 41.36733,
        "z": 0.0
      }
    },
    {
      "Frame": 351,
      "FocusedName": "Fropp",
      "LocalPosition": {
        "x": 2.7958448911810527,
        "y": 0.1,
        "z": 1.2531208972684307
      },
      "LocalRotation": {
        "x": -12.491480272812652,
        "y": -32.76611823349575,
        "z": 0
      },
      "ModelWorldPosition": {
        "x": 0,
        "y": 0,
        "z": 0
      },
      "ModelWorldRotation": {
        "x": 0.0,
        "y": 41.36733,
        "z": 0.0
      }
    },
    {
      "Frame": 352,
      "FocusedName": "Fropp",
      "LocalPosition": {
        "x": 2.7958448911810527,
        "y": 0.1,
        "z": 1.2531208972684307
      },
      "LocalRotation": {
        "x": -12.28219350269758,
        "y": -32.159901446019006,
        "z": 0
      },
      "ModelWorldPosition": {
        "x": 0,
        "y": 0,
        "z": 0
      },
      "ModelWorldRotation": {
        "x": 0.0,
        "y": 41.36733,
        "z": 0.0
      }
    }
  ]
}